minFQ/Errors.py
minFQ/__init__.py
minFQ/channelmaps.py
minFQ/endpoints.py
minFQ/fastq_handler.py
minFQ/fastq_handler_utils.py
minFQ/fastqutils.py
minFQ/flowcellmaker.py
minFQ/minFQ.py
minFQ/minknow_connection.py
minFQ/minknow_connection_utils.py
minFQ/minknowconnection.py
minFQ/minotourapi.py
minFQ/minotourapiclient.py
minFQ/run_data_tracker.py
minFQ/utils.py
minFQ/version.py
minFQ-1.4.7.dist-info/LICENSE.txt
minFQ-1.4.7.dist-info/METADATA
minFQ-1.4.7.dist-info/WHEEL
minFQ-1.4.7.dist-info/entry_points.txt
minFQ-1.4.7.dist-info/top_level.txt
minFQ-1.4.7.dist-info/RECORD
