Metadata-Version: 2.1
Name: minFQ
Version: 1.4.7
Summary: Command line interface for uploading fastq files and monitoring minKNOW for minotour.
Home-page: https://github.com/LooseLab/minotourcli
Author: Matt Loose
Author-email: matt.loose@nottingham.ac.uk
License: MIT
Keywords: nanopore quality control analysis
Platform: UNKNOWN
Classifier: Intended Audience :: Science/Research
Classifier: Topic :: Scientific/Engineering :: Bio-Informatics
Classifier: License :: OSI Approved :: MIT License
Classifier: Programming Language :: Python :: 3.5
Classifier: Programming Language :: Python :: 3.6
Classifier: Programming Language :: Python :: 3.7
Classifier: Programming Language :: Python :: 3.8
Classifier: Programming Language :: Python :: 3.9
Requires-Python: >=3.5
Requires-Dist: tqdm
Requires-Dist: python-dateutil
Requires-Dist: requests
Requires-Dist: numpy
Requires-Dist: watchdog
Requires-Dist: configargparse
Requires-Dist: grpcio
Requires-Dist: google
Requires-Dist: protobuf
Requires-Dist: pandas
Requires-Dist: ont-fast5-api
Requires-Dist: minknow-api
Requires-Dist: validators
Requires-Dist: grpcio-tools
Requires-Dist: toml
